examples/mlx90640_opencv_blob_detection.py
mlx9064x_blob_detection-1.1.1.dist-info/LICENSE
mlx9064x_blob_detection-1.1.1.dist-info/METADATA
mlx9064x_blob_detection-1.1.1.dist-info/NOTICE
mlx9064x_blob_detection-1.1.1.dist-info/WHEEL
mlx9064x_blob_detection-1.1.1.dist-info/entry_points.txt
mlx9064x_blob_detection-1.1.1.dist-info/top_level.txt
mlx9064x_blob_detection-1.1.1.dist-info/RECORD
