Metadata-Version: 2.1
Name: mlx9064x-blob-detection
Version: 1.1.1
Summary: Blob detection for MLX90640-41
Home-page: https://github.com/melexis-fir/mlx9064x-blob-detection-py
License: Apache License, Version 2.0
Download-URL: https://github.com/melexis-fir/mlx9064x-blob-detection-py/archive/V1.1.1.tar.gz
Platform: UNKNOWN
Classifier: Development Status :: 5 - Production/Stable
Classifier: Intended Audience :: Developers
Classifier: License :: OSI Approved :: Apache Software License
Classifier: Operating System :: Microsoft :: Windows
Classifier: Operating System :: POSIX
Classifier: Programming Language :: Python
Classifier: Programming Language :: Python :: 3
Classifier: Programming Language :: Python :: 3.4
Classifier: Programming Language :: Python :: 3.5
Classifier: Programming Language :: Python :: 3.6
Classifier: Programming Language :: Python :: 3.7
Classifier: Programming Language :: Python :: 3.8
Classifier: Topic :: Utilities
Requires-Dist: mlx9064x-driver (>=1.1.3)
Requires-Dist: opencv-contrib-python (>=4)
